pytorch2jax/__init__.py
pytorch2jax/pytorch2jax.py
pytorch2jax-0.1.2.dist-info/LICENSE
pytorch2jax-0.1.2.dist-info/METADATA
pytorch2jax-0.1.2.dist-info/WHEEL
pytorch2jax-0.1.2.dist-info/top_level.txt
pytorch2jax-0.1.2.dist-info/RECORD
