Metadata-Version: 2.1
Name: pytorch2jax
Version: 0.1.2
Summary: Convert PyTorch models to Jax functions and Flax models
Home-page: https://github.com/subho406/Pytorch2Jax
Author: Subhojeet Pramanik
Classifier: Programming Language :: Python :: 3.6
Classifier: Programming Language :: Python :: 3.7
Classifier: Programming Language :: Python :: 3.8
Classifier: Programming Language :: Python :: 3.9
Classifier: Programming Language :: Python :: 3.10
Requires-Python: >=3.6, <4
License-File: LICENSE
Requires-Dist: torch
Requires-Dist: jax
Requires-Dist: jaxlib
